portainer_cli/__init__.py
portainer_cli-0.3.0.data/scripts/portainer-cli
portainer_cli-0.3.0.dist-info/LICENSE
portainer_cli-0.3.0.dist-info/METADATA
portainer_cli-0.3.0.dist-info/WHEEL
portainer_cli-0.3.0.dist-info/top_level.txt
portainer_cli-0.3.0.dist-info/RECORD
