Metadata-Version: 2.1
Name: portainer-cli
Version: 0.3.0
Summary: Command line interface to easy communicate to your Portainer application.
Home-page: https://github.com/Ilhasoft/portainer-cli
Author: Ilhasoft's Web Team
Author-email: contato@ilhasoft.com.br
License: UNKNOWN
Platform: UNKNOWN
Classifier: Development Status :: 4 - Beta
Classifier: Environment :: Console
Classifier: Programming Language :: Python :: 3
Classifier: License :: OSI Approved :: MIT License
Classifier: Operating System :: OS Independent
Requires-Python: >=2.7
Requires-Dist: plac (>=1.0.0)
Requires-Dist: requests (>=2.20.0)
Requires-Dist: validators (>=0.12.2)
